sphinxcontrib_github_ribbon-0.9.0-py2.7-nspkg.pth
sphinxcontrib/github_ribbon.py
sphinxcontrib_github_ribbon-0.9.0.dist-info/DESCRIPTION.rst
sphinxcontrib_github_ribbon-0.9.0.dist-info/METADATA
sphinxcontrib_github_ribbon-0.9.0.dist-info/RECORD
sphinxcontrib_github_ribbon-0.9.0.dist-info/WHEEL
sphinxcontrib_github_ribbon-0.9.0.dist-info/metadata.json
sphinxcontrib_github_ribbon-0.9.0.dist-info/namespace_packages.txt
sphinxcontrib_github_ribbon-0.9.0.dist-info/top_level.txt
